Workbook

Sheet Sales report
A1: SALES REPORT OF JULY 2026
A4: Date | B4: Invoice No. | C4: Customer Name | D4: Product Code | E4: Product | F4: Price | G4: Unit Sold | H4: Total Sales | I4: GST 18% | J4: Net Amount
A5: 46204 | B5: IN1001 | C5: Abdullah Malik | D5: ESI1001 | E5: =IFERROR(VLOOKUP(D5,'product information'!$A$4:$C$13,2,),"") -> Keyboard Dell | F5: =IFERROR(VLOOKUP(D5,'product information'!$A$4:$C$13,3,),"") -> 450 | G5: 2 | H5: =IFERROR(F5*G5,"") -> 900 | I5: =IFERROR(H5*18%,"") -> 162 | J5: =IFERROR(H5+I5,"") -> 1062
A6: 46205 | B6: IN1002 | C6: Balaj Sheikh | D6: ESI1005 | E6: =IFERROR(VLOOKUP(D6,'product information'!$A$4:$C$13,2,),"") -> Hp Mouse | F6: =IFERROR(VLOOKUP(D6,'product information'!$A$4:$C$13,3,),"") -> 200 | G6: 12 | H6: =IFERROR(F6*G6,"") -> 2400 | I6: =IFERROR(H6*18%,"") -> 432 | J6: =IFERROR(H6+I6,"") -> 2832
A7: 46206 | B7: IN1003 | C7: Bilal Ahmed | D7: ESI1006 | E7: =IFERROR(VLOOKUP(D7,'product information'!$A$4:$C$13,2,),"") -> Headset | F7: =IFERROR(VLOOKUP(D7,'product information'!$A$4:$C$13,3,),"") -> 400 | G7: 30 | H7: =IFERROR(F7*G7,"") -> 12000 | I7: =IFERROR(H7*18%,"") -> 2160 | J7: =IFERROR(H7+I7,"") -> 14160
A8: 46207 | B8: IN1004 | C8: Faiza Hameed | D8: ESI1008 | E8: =IFERROR(VLOOKUP(D8,'product information'!$A$4:$C$13,2,),"") -> Dell Laptop | F8: =IFERROR(VLOOKUP(D8,'product information'!$A$4:$C$13,3,),"") -> 35000 | G8: 12 | H8: =IFERROR(F8*G8,"") -> 420000 | I8: =IFERROR(H8*18%,"") -> 75600 | J8: =IFERROR(H8+I8,"") -> 495600
A9: 46208 | B9: IN1005 | C9: Laiba Mansoor | D9: ESI1007 | E9: =IFERROR(VLOOKUP(D9,'product information'!$A$4:$C$13,2,),"") -> Hp Processor | F9: =IFERROR(VLOOKUP(D9,'product information'!$A$4:$C$13,3,),"") -> 1000 | G9: 19 | H9: =IFERROR(F9*G9,"") -> 19000 | I9: =IFERROR(H9*18%,"") -> 3420 | J9: =IFERROR(H9+I9,"") -> 22420
A10: 46209 | B10: IN1006 | C10: Muhammad Ali | D10: ESI1010 | E10: =IFERROR(VLOOKUP(D10,'product information'!$A$4:$C$13,2,),"") -> Hp Charger spare | F10: =IFERROR(VLOOKUP(D10,'product information'!$A$4:$C$13,3,),"") -> 10000 | G10: 13 | H10: =IFERROR(F10*G10,"") -> 130000 | I10: =IFERROR(H10*18%,"") -> 23400 | J10: =IFERROR(H10+I10,"") -> 153400
A11: 46210 | B11: IN1007 | C11: Sharjeel Ali | D11: ESI1004 | E11: =IFERROR(VLOOKUP(D11,'product information'!$A$4:$C$13,2,),"") -> Dell Monitor 18 inch | F11: =IFERROR(VLOOKUP(D11,'product information'!$A$4:$C$13,3,),"") -> 12000 | G11: 11 | H11: =IFERROR(F11*G11,"") -> 132000 | I11: =IFERROR(H11*18%,"") -> 23760 | J11: =IFERROR(H11+I11,"") -> 155760
A12: 46211 | B12: IN1008 | C12: Samreen Farhat | D12: ESI1002 | E12: =IFERROR(VLOOKUP(D12,'product information'!$A$4:$C$13,2,),"") -> Mouse Dell | F12: =IFERROR(VLOOKUP(D12,'product information'!$A$4:$C$13,3,),"") -> 200 | G12: 19 | H12: =IFERROR(F12*G12,"") -> 3800 | I12: =IFERROR(H12*18%,"") -> 684 | J12: =IFERROR(H12+I12,"") -> 4484
A13: 46212 | B13: IN1009 | C13: Usman Khan | D13: ESI1009 | E13: =IFERROR(VLOOKUP(D13,'product information'!$A$4:$C$13,2,),"") -> Speaker | F13: =IFERROR(VLOOKUP(D13,'product information'!$A$4:$C$13,3,),"") -> 1500 | G13: 8 | H13: =IFERROR(F13*G13,"") -> 12000 | I13: =IFERROR(H13*18%,"") -> 2160 | J13: =IFERROR(H13+I13,"") -> 14160
A14: 46213 | B14: IN1010 | C14: Umer Mehmood | E14: =IFERROR(VLOOKUP(D14,'product information'!$A$4:$C$13,2,),"") | F14: =IFERROR(VLOOKUP(D14,'product information'!$A$4:$C$13,3,),"") | H14: =IFERROR(F14*G14,"") | I14: =IFERROR(H14*18%,"") | J14: =IFERROR(H14+I14,"")
I15: TOTAL | J15: =SUM(J5:J14) -> 863878

Sheet product information
A3: Product code | B3: Product | C3: Price
A4: ESI1001 | B4: Keyboard Dell | C4: 450
A5: ESI1002 | B5: Mouse Dell | C5: 200
A6: ESI1003 | B6: Keyboard Hp | C6: 400
A7: ESI1004 | B7: Dell Monitor 18 inch | C7: 12000
A8: ESI1005 | B8: Hp Mouse | C8: 200
A9: ESI1006 | B9: Headset | C9: 400
A10: ESI1007 | B10: Hp Processor | C10: 1000
A11: ESI1008 | B11: Dell Laptop | C11: 35000
A12: ESI1009 | B12: Speaker | C12: 1500
A13: ESI1010 | B13: Hp Charger spare | C13: 10000
